akari/__init__.py
akari/cli.py
akari/scaffold/content/about.md
akari/scaffold/content/posts/2025-11-30-hello-world.md
akari/scaffold/static/favicon.ico
akari/scaffold/static/logo.svg
akari/scaffold/static/css/style.css
akari/scaffold/templates/base.html
akari/scaffold/templates/posts/index.html
akari/scaffold/templates/posts/item.html
akari/scaffold/templates/projects/index.html
akari/scaffold/templates/projects/item.html
akari/scaffold/templates/recipes/index.html
akari/scaffold/templates/recipes/item.html
akari_site-0.1.3.dist-info/licenses/LICENSE
akari_site-0.1.3.dist-info/METADATA
akari_site-0.1.3.dist-info/WHEEL
akari_site-0.1.3.dist-info/entry_points.txt
akari_site-0.1.3.dist-info/top_level.txt
akari_site-0.1.3.dist-info/RECORD
