Metadata-Version: 2.4
Name: akari-site
Version: 0.1.3
Summary: A minimalist static site generator
Requires-Python: >=3.11
License-File: LICENSE
Requires-Dist: PyYAML
Requires-Dist: markdown
Requires-Dist: click
Requires-Dist: watchfiles
Dynamic: license-file
